Metadata-Version: 1.0
Name: flask-rabbitmq
Version: 0.0.8
Summary: Let rabbitmq use flask development more easy! ! !
Home-page: https://github.com/PushyZqin/flask-rabbitmq
Author: Pushy
Author-email: 1437876073@qq.com
License: UNKNOWN
Platform: UNKNOWN
